{"headers": ["id", "agg", "election", "member", "party"], "types": ["id", "agg", "number", "text", "text"], "contents": [[{"col": "id", "type": "INTEGER", "data": [1, 2, 3, 4, 5, 6, 7, 8, 9, 10, 11, 12, 13, 14, 15, 16, 17]}], [{"col": "agg", "type": "INTEGER", "data": [0, 0, 0, 0, 0, 0, 0, 0, 0, 0, 0, 0, 0, 0, 0, 0, 0]}], [{"col": "c1", "type": "TEXT", "data": ["1885", "1892", "1900", "1908", "1918", "1922", "1923", "1924", "1926", "1931", "1935", "1945", "1946", "1950", "1964", "1987", "1997"]}, {"col": "c1_number", "type": "INTEGER", "data": [1885, 1892, 1900, 1908, 1918, 1922, 1923, 1924, 1926, 1931, 1935, 1945, 1946, 1950, 1964, 1987, 1997]}], [{"col": "c2", "type": "TEXT", "data": ["william james beadel", "thomas usborne", "sir carne rasch, bt", "e. g. pretyman", "e. g. pretyman", "e. g. pretyman", "sydney walter robinson", "sir henry honywood curtis-bennett", "charles kenneth howard-bury", "sir vivian leonard henderson", "john macnamara", "ernest millington", "ernest millington", "sir hubert ashton", "norman st john-stevas", "simon burns", "constituency abolished - see west chelmsford,\nmaldon and chelmsford east, rayleigh"]}], [{"col": "c3", "type": "TEXT", "data": ["conservative", "conservative", "conservative", "conservative", "coalition conservative", "conservative", "liberal", "conservative", "conservative", "conservative", "conservative", "common wealth", "labour", "conservative", "conservative", "conservative", "constituency abolished - see west chelmsford,\nmaldon and chelmsford east, rayleigh"]}]], "is_list": {"id": false, "agg": false, "c1": false, "c1_number": false, "c2": false, "c3": false}}