{"headers": ["id", "agg", "weapon name", "caliber (mm)", "range (max)", "warhead"], "types": ["id", "agg", "text", "unitnum", "unitnum(unitnum)", "unitnum(unitnum)"], "contents": [[{"col": "id", "type": "INTEGER", "data": [1, 2, 3, 4, 5, 6, 7, 8]}], [{"col": "agg", "type": "INTEGER", "data": [0, 0, 0, 0, 0, 0, 0, 0]}], [{"col": "c1", "type": "TEXT", "data": ["m-8", "m-13", "m-13dd", "m-13uk", "m-20", "m-30", "m-31", "m-31uk"]}], [{"col": "c2", "type": "TEXT", "data": ["82 mm", "132 mm", "132 mm", "132 mm", "132 mm", "300 mm", "300 mm", "300 mm"]}, {"col": "c2_number", "type": "REAL", "data": [82.0, 132.0, 132.0, 132.0, 132.0, 300.0, 300.0, 300.0]}], [{"col": "c3", "type": "TEXT", "data": ["5,900 m (6,500 yd)", "8,740 m (9,560 yd)", "11,800 m (12,900 yd)", "7,900 m (8,600 yd)", "5,050 m (5,520 yd)", "2,800 m (3,100 yd)", "4,325 m (4,730 yd)", "4,000 m (4,400 yd)"]}, {"col": "c3_first", "type": "TEXT", "data": ["5,900 m", "8,740 m", "11,800 m", "7,900 m", "5,050 m", "2,800 m", "4,325 m", "4,000 m"]}, {"col": "c3_second", "type": "TEXT", "data": ["6,500 yd", "9,560 yd", "12,900 yd", "8,600 yd", "5,520 yd", "3,100 yd", "4,730 yd", "4,400 yd"]}, {"col": "c3_first_number", "type": "REAL", "data": [5900.0, 8740.0, 11800.0, 7900.0, 5050.0, 2800.0, 4325.0, 4000.0]}, {"col": "c3_second_number", "type": "REAL", "data": [6500.0, 9560.0, 12900.0, 8600.0, 5520.0, 3100.0, 4730.0, 4400.0]}], [{"col": "c4", "type": "TEXT", "data": ["0.64 kg (1.4 lb)", "4.9 kg (11 lb)", "4.9 kg (11 lb)", "4.9 kg (11 lb)", "18.4 kg (41 lb)", "28.9 kg (64 lb)", "28.9 kg (64 lb)", "28.9 kg (64 lb)"]}, {"col": "c4_first", "type": "TEXT", "data": ["0.64 kg", "4.9 kg", "4.9 kg", "4.9 kg", "18.4 kg", "28.9 kg", "28.9 kg", "28.9 kg"]}, {"col": "c4_second", "type": "TEXT", "data": ["1.4 lb", "11 lb", "11 lb", "11 lb", "41 lb", "64 lb", "64 lb", "64 lb"]}, {"col": "c4_first_number", "type": "REAL", "data": [0.64, 4.9, 4.9, 4.9, 18.4, 28.9, 28.9, 28.9]}, {"col": "c4_second_number", "type": "REAL", "data": [1.4, 11.0, 11.0, 11.0, 41.0, 64.0, 64.0, 64.0]}]], "is_list": {"id": false, "agg": false, "c1": false, "c2": false, "c2_number": false, "c3": false, "c3_first": false, "c3_second": false, "c3_first_number": false, "c3_second_number": false, "c4": false, "c4_first": false, "c4_second": false, "c4_first_number": false, "c4_second_number": false}}