{"headers": ["id", "agg", "party", "votes", "%", "seats", "+/-"], "types": ["id", "agg", "text", "number", "number", "number", "number"], "contents": [[{"col": "id", "type": "INTEGER", "data": [1, 2, 3, 4, 5, 6, 7, 8, 9, 10, 11, 12]}], [{"col": "agg", "type": "INTEGER", "data": ["0", "0", "0", "0", "0", "0", "0", "0", "0", "0", "1", "1"]}], [{"col": "c1", "type": "TEXT", "data": ["swedish social democratic party", "moderate party", "left party", "christian democrats", "centre party", "liberal people's party", "green party", "sweden democrats", "other parties", "invalid/blank votes", "total", "registered voters/turnout"]}], [{"col": "c2", "type": "TEXT", "data": ["1914426", "1204926", "631011", "619046", "269762", "248076", "236699", "19624", "117552", "113466", "5374588", "6603129"]}, {"col": "c2_number", "type": "REAL", "data": [1914426.0, 1204926.0, 631011.0, 619046.0, 269762.0, 248076.0, 236699.0, 19624.0, 117552.0, 113466.0, 5374588.0, 6603129.0]}], [{"col": "c3", "type": "TEXT", "data": ["36.4", "22.9", "12", "11.8", "5.1", "4.7", "4.5", "0.4", "2.2", null, "100", "81.4"]}, {"col": "c3_number", "type": "REAL", "data": [36.4, 22.9, 12.0, 11.8, 5.1, 4.7, 4.5, 0.4, 2.2, null, 100.0, 81.4]}], [{"col": "c4", "type": "TEXT", "data": ["131", "82", "43", "42", "18", "17", "16", "0", "0", null, "349", null]}, {"col": "c4_number", "type": "REAL", "data": [131.0, 82.0, 43.0, 42.0, 18.0, 17.0, 16.0, 0.0, 0.0, null, 349.0, null]}], [{"col": "c5", "type": "TEXT", "data": ["-30", "2", "21", "27", "-9", "-9", "-2", "0", "0", null, "0", null]}, {"col": "c5_number", "type": "REAL", "data": [-30, 2.0, 21.0, 27.0, -9, -9, -2, 0.0, 0.0, null, 0.0, null]}]], "is_list": {"id": false, "agg": false, "c1": false, "c2": false, "c2_number": false, "c3": false, "c3_number": false, "c4": false, "c4_number": false, "c5": false, "c5_number": false}}