{"headers": ["id", "agg", "version", "date", "development cycle", "size (in kb)", "download", "notes"], "types": ["id", "agg", "text", "date", "text", "number", "<c,text>", "text(text)"], "contents": [[{"col": "id", "type": "INTEGER", "data": [1, 2, 3, 4, 5, 6, 7, 8, 9, 10, 11, 12, 13, 14]}], [{"col": "agg", "type": "INTEGER", "data": [0, 0, 0, 0, 0, 0, 0, 0, 0, 0, 0, 0, 0, 0]}], [{"col": "c1", "type": "TEXT", "data": ["0.1", "0.2", "0.3", "0.4", "0.5", "0.6", "0.8", "0.9", "0.9", "0.9", "1", "1.01", "1.01a", "2"]}], [{"col": "c2", "type": "TEXT", "data": ["9 june 1993", "14 june 1993", "16 june 1993", "18 june 1993", "24 june 1993", "30 june 1993", "5 november 1993", "12 november 1993", "16 november 1993", "22 november 1993", "17 february 1994", null, "17 march 1994", null]}, {"col": "c2_number", "type": "INTEGER", "data": [9, 14, 16, 18, 24, 30, 5, 12, 16, 22, 17, null, 17, null]}, {"col": "c2_parsed", "type": "TEXT", "data": ["1993-06-09", "1993-06-14", "1993-06-16", "1993-06-18", "1993-06-24", "1993-06-30", "1993-11-05", "1993-11-12", "1993-11-16", "1993-11-22", "1994-02-17", null, "1994-03-17", null]}, {"col": "c2_year", "type": "INTEGER", "data": [1993, 1993, 1993, 1993, 1993, 1993, 1993, 1993, 1993, 1993, 1994, null, 1994, null]}, {"col": "c2_month", "type": "INTEGER", "data": [6, 6, 6, 6, 6, 6, 11, 11, 11, 11, 2, null, 3, null]}, {"col": "c2_day", "type": "INTEGER", "data": [9, 14, 16, 18, 24, 30, 5, 12, 16, 22, 17, null, 17, null]}], [{"col": "c3", "type": "TEXT", "data": ["beta", "beta", "beta", "beta", "beta", "beta", "beta", "beta-pre", "beta", "winsock alpha r9.2", "release", "release", "release", "alpha"]}], [{"col": "c4", "type": "TEXT", "data": [null, null, null, null, null, null, null, null, null, null, null, null, "521", null]}, {"col": "c4_number", "type": "REAL", "data": [null, null, null, null, null, null, null, null, null, null, null, null, 521.0, null]}], [{"col": "c5", "type": "TEXT", "data": ["evolt", null, null, null, null, null, null, null, null, null, "evolt", null, "[5], evolt", null]}, {"col": "c5_list", "type": "LIST TEXT", "data": [["evolt"], [], [], [], [], [], [], [], [], [], ["evolt"], [], ["[5]", "evolt"], []]}, {"col": "c5_length", "type": "INTEGER", "data": [1, 0, 0, 0, 0, 0, 0, 0, 0, 0, 1, 0, 2, 0]}], [{"col": "c6", "type": "TEXT", "data": [null, "changelog", "changelog", "changelog", "changelog", "changelog", "changelog (distinct version discontinued)", null, "changelog", null, null, null, "changelog", "development ceased"]}, {"col": "c6_first", "type": "TEXT", "data": [null, "changelog", "changelog", "changelog", "changelog", "changelog", "changelog", null, "changelog", null, null, null, "changelog", "development ceased"]}, {"col": "c6_second", "type": "TEXT", "data": [null, null, null, null, null, null, "distinct version discontinued", null, null, null, null, null, null, null]}]], "is_list": {"id": false, "agg": false, "c1": false, "c2": false, "c2_number": false, "c2_parsed": false, "c2_year": false, "c2_month": false, "c2_day": false, "c3": false, "c4": false, "c4_number": false, "c5": false, "c5_list": true, "c5_length": false, "c6": false, "c6_first": false, "c6_second": false}}