{"headers": ["id", "agg", "margin", "teams", "venue", "season"], "types": ["id", "agg", "unitnum", "text", "address", "number"], "contents": [[{"col": "id", "type": "INTEGER", "data": [1, 2, 3, 4, 5, 6]}], [{"col": "agg", "type": "INTEGER", "data": [0, 0, 0, 0, 0, 0]}], [{"col": "c1", "type": "TEXT", "data": ["192 runs", "72 runs", "57 runs", "36 runs", "24 runs", "16 runs"]}, {"col": "c1_number", "type": "REAL", "data": [192.0, 72.0, 57.0, 36.0, 24.0, 16.0]}], [{"col": "c2", "type": "TEXT", "data": ["kent (205 & 512-9 d) beat essex (370 & 155)", "kent (117 & 332) beat surrey (301-8 d & 76)", "kent (151 & 348) beat middlesex (305-5 d & 137)", "kent (127 & 198) beat australia (229 & 60)", "kent (115 & 389) beat gloucestershire (351 & 129)", "kent (120 & 176) beat cambridgeshire (206 & 74)"]}], [{"col": "c3", "type": "TEXT", "data": ["county ground, chelmsford", "woodbridge road, guildford", "hesketh park, dartford", "st lawrence ground, canterbury", "mote park, maidstone", "mote park, maidstone"]}, {"col": "c3_address", "type": "LIST TEXT", "data": [["county ground", "chelmsford"], ["woodbridge road", "guildford"], ["hesketh park", "dartford"], ["st lawrence ground", "canterbury"], ["mote park", "maidstone"], ["mote park", "maidstone"]]}], [{"col": "c4", "type": "TEXT", "data": ["2009", "1992", "1976", "1893", "1925", "1863"]}, {"col": "c4_number", "type": "INTEGER", "data": [2009, 1992, 1976, 1893, 1925, 1863]}]], "is_list": {"id": false, "agg": false, "c1": false, "c1_number": false, "c2": false, "c3": false, "c3_address": true, "c4": false, "c4_number": false}}