{"headers": ["id", "agg", "player", "year", "round", "result", "opponent"], "types": ["id", "agg", "text", "number", "text", "score", "text"], "contents": [[{"col": "id", "type": "INTEGER", "data": [1, 2, 3, 4, 5, 6, 7]}], [{"col": "agg", "type": "INTEGER", "data": [0, 0, 0, 0, 0, 0, 0]}], [{"col": "c1", "type": "TEXT", "data": ["raymond van barneveld", "raymond van barneveld", "adrian lewis", "dean winstanley", "michael van gerwen", "terry jenkins", "kyle anderson"]}], [{"col": "c2", "type": "TEXT", "data": ["2009", "2010", "2011", "2013", "2013", "2014", "2014"]}, {"col": "c2_number", "type": "INTEGER", "data": [2009, 2010, 2011, 2013, 2013, 2014, 2014]}], [{"col": "c3", "type": "TEXT", "data": ["quarter-final", "2nd round", "final", "2nd round", "semi final", "1st round", "1st round"]}], [{"col": "c4", "type": "TEXT", "data": ["won", "won", "won", "lost", "won", "lost", "lost"]}, {"col": "c4_result", "type": "TEXT", "data": ["won", "won", "won", "lost", "won", "lost", "lost"]}], [{"col": "c5", "type": "TEXT", "data": ["jelle klaasen", "brendan dolan", "gary anderson", "vincent van der voort", "james wade", "per laursen", "ian white"]}]], "is_list": {"id": false, "agg": false, "c1": false, "c2": false, "c2_number": false, "c3": false, "c4": false, "c4_result": false, "c5": false}}