{"headers": ["id", "agg", "event", "record", "athlete", "date", "meet", "place"], "types": ["id", "agg", "text", "text", "text", "timespan", "text", "address"], "contents": [[{"col": "id", "type": "INTEGER", "data": [1, 2, 3, 4, 5, 6, 7, 8, 9, 10, 11, 12, 13, 14, 15, 16, 17, 18, 19, 20, 21, 22, 23, 24, 25, 26, 27, 28, 29, 30, 31, 32, 33, 34, 35, 36, 37, 38, 39, 40, 41, 42, 43, 44, 45, 46, 47, 48, 49]}], [{"col": "agg", "type": "INTEGER", "data": [0, 0, 0, 0, 0, 0, 0, 0, 0, 0, 0, 0, 0, 0, 0, 0, 0, 0, 0, 0, 0, 0, 0, 0, 0, 0, 0, 0, 0, 0, 0, 0, 0, 0, 0, 0, 0, 0, 0, 0, 0, 0, 0, 0, 0, 0, 0, 0, 0]}], [{"col": "c1", "type": "TEXT", "data": ["100 m", "200 m", "300 m", "400 m", "800 m", "1500 m", "mile", "2000 m", "3000 m", "two miles", "5000 m", "10000 m", "10 km (road)", "15 km (road)", "20000 m (track)", "20 km (road)", "one hour", "half marathon", "half marathon", "25 km (road)", "25 km (road)", "30 km (road)", "30 km (road)", "marathon", "marathon", "110 m hurdles", "400 m hurdles", "3000 m steeplechase", "high jump", "pole vault", "long jump", "triple jump", "shot put", "discus throw", "hammer throw", "javelin throw", "decathlon", "decathlon", "5000 m walk (track)", "5 km walk (road)", "10000 m walk (track)", "10000 m walk (track)", "10 km walk (road)", "20000 m walk (track)", "20 km walk (road)", "50000 m walk (track)", "50 km walk (road)", "4x100 m relay", "4x400 m relay"]}], [{"col": "c2", "type": "TEXT", "data": ["10.21 (+0.1 m/s)", "20.36 (+0.3 m/s)", "32.87", "44.31", "01:45.9", "03:36.7", "03:58.2", "05:03.4", "07:35.7", "08:23.8", "13:07.8", "27:08.2", "27:41:00", "42:36:00", "56:55.6", "58:26:00", "21101 m", "1:00:14 am", "1:00:28", "1:16:26", "1:14:54", "1:30:19", "1:31:46", "2:07:19 am", "2:08:30", "13.81 (+0.8 m/s)", "49.41", "08:25.7", "2.30 m", "5.82 m", "8.46 m (+1.3 m/s)", "16.63 m (-0.1 m/s)", "19.91 m", "60.45 m", "71.46 m", "80.46 m", "7614 pts (ht)", "10.2 (+0.1 m/s) (100 m), 7.72 m (+1.3 m/s) (long jump), 12.55 m (shot put), 1.74 m (high jump), 46.33 (400 m) /\n15.73 (0.0 m/s) (110 m hurdles), 38.32 m (discus), 4.40 m (pole vault), 57.28 m (javelin), 4:52.35 (1500 m)", "18:40.1", "19:17", "38:24.0", "38:26.4", "38:31:00", "17:25.6", "1:17:26", "41:38.4", "3:41:20", "39.32", "03:03.2"]}], [{"col": "c3", "type": "TEXT", "data": ["carlos villasenor garcia", "jose carlos herrera", "juan pedro toledo", "alejandro cardenas", "james eichberger", "pablo solares", "juan luis barrios", "arturo barrios", "arturo barrios", "juan luis barrios", "arturo barrios", "arturo barrios", "arturo barrios", "arturo barrios", "arturo barrios", "juan carlos romero", "arturo barrios", "armando quintanilla", "german silva", "andres espinosa", "juan luis barrios", "juan luis barrios", "andres espinosa", "andres espinosa", "dionicio ceron pizarro", "roberto carmona", "jesus aguilasocho", "salvador miranda", "gerardo martinez", "giovanni lanaro", "luis rivera", "alberto alvarez", "stephen saenz", "mario cota", "guillermo guzman", "juan de la garza", "alejandro cardenas", "10.2 (+0.1 m/s) (100 m), 7.72 m (+1.3 m/s) (long jump), 12.55 m (shot put), 1.74 m (high jump), 46.33 (400 m) /\n15.73 (0.0 m/s) (110 m hurdles), 38.32 m (discus), 4.40 m (pole vault), 57.28 m (javelin), 4:52.35 (1500 m)", "eder sanchez", "eder sanchez", "bernardo segura rivera", "daniel garcia", "eder sanchez", "bernardo segura", "bernardo segura", "raul gonzalez", "raul gonzalez", "mexico\ngenaro rojas\neduardo nava\nherman adam\nalejandro cardenas", "mexico\nalejandro cardenas\noscar juanz\nroberto carvajal\njuan pedro toledo"]}], [{"col": "c4", "type": "TEXT", "data": ["11-jul-97", "23-mar-14", "14-sep-00", "26-aug-99", "27-jul-13", "30-may-09", "15-apr-07", "10-jul-89", "10-jul-89", "10-jun-07", "14-jul-89", "18-aug-89", "1-mar-86", "29-jun-86", "30-mar-91", "11-oct-09", "30-mar-91", "21-jan-96", "24-sep-94", "28-sep-03", "6-mar-11", "6-mar-11", "28-sep-03", "18-apr-94", "2-apr-95", "22-jul-88", "20-sep-85", "8-jul-00", "15-apr-07", "15-apr-07", "12-jul-13", "23-mar-14", "26-may-12", "20-apr-12", "14-jun-92", "28-jun-92", "10-11 may 1996", null, "28-feb-09", "8-dec-06", "7-may-94", "17-may-97", "19-sep-09", "7-may-94", "7-may-94", "25-may-79", "11-jun-78", "21-jun-92", "11-aug-01"]}, {"col": "c4_minimum_number", "type": "INTEGER", "data": [1997, 2014, 2000, 1999, 2013, 2009, 2007, 1989, 1989, 2007, 1989, 1989, 1986, 1986, 1991, 2009, 1991, 1996, 1994, 2003, 2011, 2011, 2003, 1994, 1995, 1988, 1985, 2000, 2007, 2007, 2013, 2014, 2012, 2012, 1992, 1992, 1996, null, 2009, 2006, 1994, 1997, 2009, 1994, 1994, 1979, 1978, 1992, 2001]}, {"col": "c4_minimum_parsed", "type": "TEXT", "data": ["1997-07-11", "2014-03-23", "2000-09-14", "1999-08-26", "2013-07-27", "2009-05-30", "2007-04-15", "1989-07-10", "1989-07-10", "2007-06-10", "1989-07-14", "1989-08-18", "1986-03-01", "1986-06-29", "1991-03-30", "2009-10-11", "1991-03-30", "1996-01-21", "1994-09-24", "2003-09-28", "2011-03-06", "2011-03-06", "2003-09-28", "1994-04-18", "1995-04-02", "1988-07-22", "1985-09-20", "2000-07-08", "2007-04-15", "2007-04-15", "2013-07-12", "2014-03-23", "2012-05-26", "2012-04-20", "1992-06-14", "1992-06-28", "1996-05-10", null, "2009-02-28", "2006-12-08", "1994-05-07", "1997-05-17", "2009-09-19", "1994-05-07", "1994-05-07", "1979-05-25", "1978-06-11", "1992-06-21", "2001-08-11"]}, {"col": "c4_minimum_day", "type": "INTEGER", "data": [11, 23, 14, 26, 27, 30, 15, 10, 10, 10, 14, 18, 1, 29, 30, 11, 30, 21, 24, 28, 6, 6, 28, 18, 2, 22, 20, 8, 15, 15, 12, 23, 26, 20, 14, 28, 10, null, 28, 8, 7, 17, 19, 7, 7, 25, 11, 21, 11]}, {"col": "c4_minimum_month", "type": "INTEGER", "data": [7, 3, 9, 8, 7, 5, 4, 7, 7, 6, 7, 8, 3, 6, 3, 10, 3, 1, 9, 9, 3, 3, 9, 4, 4, 7, 9, 7, 4, 4, 7, 3, 5, 4, 6, 6, 5, null, 2, 12, 5, 5, 9, 5, 5, 5, 6, 6, 8]}, {"col": "c4_minimum_year", "type": "INTEGER", "data": [1997, 2014, 2000, 1999, 2013, 2009, 2007, 1989, 1989, 2007, 1989, 1989, 1986, 1986, 1991, 2009, 1991, 1996, 1994, 2003, 2011, 2011, 2003, 1994, 1995, 1988, 1985, 2000, 2007, 2007, 2013, 2014, 2012, 2012, 1992, 1992, 1996, null, 2009, 2006, 1994, 1997, 2009, 1994, 1994, 1979, 1978, 1992, 2001]}, {"col": "c4_maximum_number", "type": "INTEGER", "data": [1997, 2014, 2000, 1999, 2013, 2009, 2007, 1989, 1989, 2007, 1989, 1989, 1986, 1986, 1991, 2009, 1991, 1996, 1994, 2003, 2011, 2011, 2003, 1994, 1995, 1988, 1985, 2000, 2007, 2007, 2013, 2014, 2012, 2012, 1992, 1992, 1996, null, 2009, 2006, 1994, 1997, 2009, 1994, 1994, 1979, 1978, 1992, 2001]}, {"col": "c4_maximum_parsed", "type": "TEXT", "data": ["1997-07-11", "2014-03-23", "2000-09-14", "1999-08-26", "2013-07-27", "2009-05-30", "2007-04-15", "1989-07-10", "1989-07-10", "2007-06-10", "1989-07-14", "1989-08-18", "1986-03-01", "1986-06-29", "1991-03-30", "2009-10-11", "1991-03-30", "1996-01-21", "1994-09-24", "2003-09-28", "2011-03-06", "2011-03-06", "2003-09-28", "1994-04-18", "1995-04-02", "1988-07-22", "1985-09-20", "2000-07-08", "2007-04-15", "2007-04-15", "2013-07-12", "2014-03-23", "2012-05-26", "2012-04-20", "1992-06-14", "1992-06-28", "1996-05-11", null, "2009-02-28", "2006-12-08", "1994-05-07", "1997-05-17", "2009-09-19", "1994-05-07", "1994-05-07", "1979-05-25", "1978-06-11", "1992-06-21", "2001-08-11"]}, {"col": "c4_maximum_day", "type": "INTEGER", "data": [11, 23, 14, 26, 27, 30, 15, 10, 10, 10, 14, 18, 1, 29, 30, 11, 30, 21, 24, 28, 6, 6, 28, 18, 2, 22, 20, 8, 15, 15, 12, 23, 26, 20, 14, 28, 11, null, 28, 8, 7, 17, 19, 7, 7, 25, 11, 21, 11]}, {"col": "c4_maximum_month", "type": "INTEGER", "data": [7, 3, 9, 8, 7, 5, 4, 7, 7, 6, 7, 8, 3, 6, 3, 10, 3, 1, 9, 9, 3, 3, 9, 4, 4, 7, 9, 7, 4, 4, 7, 3, 5, 4, 6, 6, 5, null, 2, 12, 5, 5, 9, 5, 5, 5, 6, 6, 8]}, {"col": "c4_maximum_year", "type": "INTEGER", "data": [1997, 2014, 2000, 1999, 2013, 2009, 2007, 1989, 1989, 2007, 1989, 1989, 1986, 1986, 1991, 2009, 1991, 1996, 1994, 2003, 2011, 2011, 2003, 1994, 1995, 1988, 1985, 2000, 2007, 2007, 2013, 2014, 2012, 2012, 1992, 1992, 1996, null, 2009, 2006, 1994, 1997, 2009, 1994, 1994, 1979, 1978, 1992, 2001]}], [{"col": "c5", "type": "TEXT", "data": ["mexican championships", "relevos del tec", null, "world championships", "memorial rasschaert - flanders cup", "reebok grand prix", "mt. sac relays", null, null, "prefontaine classic", null, "istaf", "continental homes 10k", "cascade run off", null, "world half marathon championships", null, "tokyo half marathon", "world half marathon championships", "berlin marathon", "lala marathon", "lala marathon", "berlin marathon", "boston marathon", "london marathon", "ibero-american championships", "copa de las americas", "encuentro nacional de fondo", "mt. sac relays", "mt. sac relays", "universiade", "relevos del tec", "ncaa division i east preliminary round", "mt. sac relays", null, null, "ibero-american championships", null, "sydney track classic", "gran premio internacional", null, null, "iaaf world race walking challenge", null, null, null, null, null, "world championships"]}], [{"col": "c6", "type": "TEXT", "data": ["toluca, mexico", "monterrey, mexico", "sydney, australia", "seville, spain", "ninove, belgium", "new york city, united states", "walnut, united states", "nice, france", "nice, france", "eugene, united states", "london, united kingdom", "berlin, germany", "phoenix, united states", "portland, united states", "la fleche, france", "birmingham, united kingdom", "la fleche, france", "tokyo, japan", "oslo, norway", "berlin, berlin", "torreon, mexico", "torreon, mexico", "berlin, germany", "boston, united states", "london, united kingdom", "mexico city, mexico", "san juan, puerto rico", "barakaldo, spain", "walnut, united states", "walnut, united states", "kazan, russia", "monterrey, mexico", "jacksonville, united states", "walnut, united states", "mexico city, mexico", "mexico city, mexico", "medellin, colombia", null, "sydney, australia", "granada, spain", "fana, norway", "s\u00f8nder-omme, denmark", "saransk, russia", "bergen, norway", "fana, norway", "bergen, norway", "podebrady, czech republic", "mexico city, mexico", "edmonton, canada"]}, {"col": "c6_address", "type": "LIST TEXT", "data": [["toluca", "mexico"], ["monterrey", "mexico"], ["sydney", "australia"], ["seville", "spain"], ["ninove", "belgium"], ["new york city", "united states"], ["walnut", "united states"], ["nice", "france"], ["nice", "france"], ["eugene", "united states"], ["london", "united kingdom"], ["berlin", "germany"], ["phoenix", "united states"], ["portland", "united states"], ["la fleche", "france"], ["birmingham", "united kingdom"], ["la fleche", "france"], ["tokyo", "japan"], ["oslo", "norway"], ["berlin", "berlin"], ["torreon", "mexico"], ["torreon", "mexico"], ["berlin", "germany"], ["boston", "united states"], ["london", "united kingdom"], ["mexico city", "mexico"], ["san juan", "puerto rico"], ["barakaldo", "spain"], ["walnut", "united states"], ["walnut", "united states"], ["kazan", "russia"], ["monterrey", "mexico"], ["jacksonville", "united states"], ["walnut", "united states"], ["mexico city", "mexico"], ["mexico city", "mexico"], ["medellin", "colombia"], [], ["sydney", "australia"], ["granada", "spain"], ["fana", "norway"], ["s\u00f8nder-omme", "denmark"], ["saransk", "russia"], ["bergen", "norway"], ["fana", "norway"], ["bergen", "norway"], ["podebrady", "czech republic"], ["mexico city", "mexico"], ["edmonton", "canada"]]}]], "is_list": {"id": false, "agg": false, "c1": false, "c2": false, "c3": false, "c4": false, "c4_minimum_number": false, "c4_minimum_parsed": false, "c4_minimum_day": false, "c4_minimum_month": false, "c4_minimum_year": false, "c4_maximum_number": false, "c4_maximum_parsed": false, "c4_maximum_day": false, "c4_maximum_month": false, "c4_maximum_year": false, "c5": false, "c6": false, "c6_address": true}}