{"headers": ["id", "agg", "week #", "theme", "song choice", "original artist", "order #", "result"], "types": ["id", "agg", "text", "text", "text", "text", "number", "text"], "contents": [[{"col": "id", "type": "INTEGER", "data": [1, 2, 3, 4, 5, 6, 7, 8, 9, 10, 11, 12, 13, 14, 15, 16, 17, 18, 19]}], [{"col": "agg", "type": "INTEGER", "data": [0, 0, 0, 0, 0, 0, 0, 0, 0, 0, 0, 0, 0, 0, 0, 0, 0, 0, 0]}], [{"col": "c1", "type": "TEXT", "data": ["audition", "theater", "top 30", "top 10", "top 9", "top 8", "top 7", "top 6", "top 5", "top 5", "top 4", "top 4", "top 3", "top 3", "top 2", "top 2", "top 2", "top 2", "top 2"]}], [{"col": "c2", "type": "TEXT", "data": ["auditioner's choice", "first solo", "semi-final/group 3", "my idol", "male singers", "female singers", "birth year songs", "jovem pan hits", "jovem guarda", "jovem guarda", "brazil regional", "brazil regional", "contestant's choice", "contestant's choice", "winner's single", "challenging songs", "judge's choice", "best of the season", "celebrity duet"]}], [{"col": "c3", "type": "TEXT", "data": ["\"tempos modernos\"", "\"a sombra da maldade\"", "\"noite do prazer\"", "\"paraiso\"", "\"ultimo romantico\"", "\"lanterna dos afogados\"", "\"frisson\"", "\"do seu lado\"", "\"o bom\"", "\"vem me ajudar\"", "\"eva\"", "\"admiravel gado novo\"", "\"as sete vampiras\"", "\"eu me rendo\"", "\"deixo a voz me levar\"", "\"queixa\"", "\"quero te encontrar\"", "\"paraiso\"", "\"admiravel gado novo\"\nwith ze ramalho"]}], [{"col": "c4", "type": "TEXT", "data": ["lulu santos", "cidade negra", "claudio zoli", "claudio zoli", "lulu santos", "cassia eller", "tunai", "jota quest", "eduardo araujo", "the fevers", "radio taxi", "ze ramalho", "leo jaime", "fabio junior", "leandro lopes", "caetano veloso", "kid abelha", "claudio zoli", "ze ramalho"]}], [{"col": "c5", "type": "TEXT", "data": [null, null, "10", "6", "8", "1", "4", "6", "3", "8", "3", "7", "2", "5", "2", "4", "6", "8", "10"]}, {"col": "c5_number", "type": "REAL", "data": [null, null, 10.0, 6.0, 8.0, 1.0, 4.0, 6.0, 3.0, 8.0, 3.0, 7.0, 2.0, 5.0, 2.0, 4.0, 6.0, 8.0, 10.0]}], [{"col": "c6", "type": "TEXT", "data": ["advanced", "advanced", "advanced", "safe", "safe", "safe", "safe", "safe", "safe", "safe", "safe", "safe", "safe", "safe", "winner", "winner", "winner", "winner", "winner"]}]], "is_list": {"id": false, "agg": false, "c1": false, "c2": false, "c3": false, "c4": false, "c5": false, "c5_number": false, "c6": false}}